{
  "id": "response-2",
  "response_id": "response-2",
  "summary": "HTTP 200",
  "request_method": null,
  "request_url": null,
  "content_preview": "[{\"id\":\"1\",\"name\":\"Google Pixel 6 Pro\",\"data\":{\"color\":\"Cloudy White\",\"capacity\":\"128 GB\"}},{\"id\":\"2\",\"name\":\"Apple iPhone 12 Mini, 256GB, Blue\",\"data\":null},{\"id\":\"3\",\"name\":\"Apple iPhone 12 Pro Max\",\"data\":{\"color\":\"Cloudy White\",\"capacity GB\":512}},{\"id\":\"4\",\"name\":\"Apple iPhone 11, 64GB\",\"data\":{\"price\":389.99,\"color\":\"Purple\"}},{\"id\":\"5\",\"name\":\"Samsung Galaxy Z Fold2\",\"data\":{\"price\":689.99,",
  "content_type": "application/json;charset=UTF-8",
  "header_count": 19,
  "size_bytes": 1239,
  "model": null,
  "tokens": null,
  "tags": [],
  "created_at": null,
  "detail": {
    "request_headers": [],
    "response_headers": []
  }
}